{
  "completions": [
    {
      "created_at": 1602594988,
      "id": 308001,
      "lead_time": 59.23,
      "result": [
        {
          "from_name": "kp-1",
          "id": "jcjFR9lAEZ",
          "image_rotation": 0,
          "original_height": 1080,
          "original_width": 1920,
          "parent_id": null,
          "source": "$img",
          "to_name": "img-1",
          "type": "keypointlabels",
          "value": {
            "keypointlabels": [
              "nose"
            ],
            "width": 0.2932551319648094,
            "x": 50.29325513196481,
            "y": 30.026109660574413
          }
        },
        {
          "from_name": "kp-1",
          "id": "y5HFRN8LHP",
          "image_rotation": 0,
          "original_height": 1080,
          "original_width": 1920,
          "parent_id": null,
          "source": "$img",
          "to_name": "img-1",
          "type": "keypointlabels",
          "value": {
            "keypointlabels": [
              "leftEye"
            ],
            "width": 0.2932551319648094,
            "x": 51.02639296187683,
            "y": 29.242819843342037
          }
        },
        {
          "from_name": "kp-1",
          "id": "iSJ7KVp7td",
          "image_rotation": 0,
          "original_height": 1080,
          "original_width": 1920,
          "parent_id": null,
          "source": "$img",
          "to_name": "img-1",
          "type": "keypointlabels",
          "value": {
            "keypointlabels": [
              "leftEar"
            ],
            "width": 0.2932551319648094,
            "x": 51.759530791788855,
            "y": 30.287206266318538
          }
        },
        {
          "from_name": "kp-1",
          "id": "OtSDamlwCo",
          "image_rotation": 0,
          "original_height": 1080,
          "original_width": 1920,
          "parent_id": null,
          "source": "$img",
          "to_name": "img-1",
          "type": "keypointlabels",
          "value": {
            "keypointlabels": [
              "leftShoulder"
            ],
            "width": 0.2932551319648094,
            "x": 52.34604105571847,
            "y": 35.24804177545692
          }
        },
        {
          "from_name": "kp-1",
          "id": "uxWsszvral",
          "image_rotation": 0,
          "original_height": 1080,
          "original_width": 1920,
          "parent_id": null,
          "source": "$img",
          "to_name": "img-1",
          "type": "keypointlabels",
          "value": {
            "keypointlabels": [
              "rightShoulder"
            ],
            "width": 0.2932551319648094,
            "x": 48.97360703812317,
            "y": 34.46475195822455
          }
        },
        {
          "from_name": "kp-1",
          "id": "IHXJy9JrOG",
          "image_rotation": 0,
          "original_height": 1080,
          "original_width": 1920,
          "parent_id": null,
          "source": "$img",
          "to_name": "img-1",
          "type": "keypointlabels",
          "value": {
            "keypointlabels": [
              "leftElbow"
            ],
            "width": 0.2932551319648094,
            "x": 53.225806451612904,
            "y": 42.03655352480418
          }
        },
        {
          "from_name": "kp-1",
          "id": "Y8wyjZwJ6T",
          "image_rotation": 0,
          "original_height": 1080,
          "original_width": 1920,
          "parent_id": null,
          "source": "$img",
          "to_name": "img-1",
          "type": "keypointlabels",
          "value": {
            "keypointlabels": [
              "rightElbow"
            ],
            "width": 0.2932551319648094,
            "x": 46.62756598240469,
            "y": 35.50913838120105
          }
        },
        {
          "from_name": "kp-1",
          "id": "om2uxMhUsA",
          "image_rotation": 0,
          "original_height": 1080,
          "original_width": 1920,
          "parent_id": null,
          "source": "$img",
          "to_name": "img-1",
          "type": "keypointlabels",
          "value": {
            "keypointlabels": [
              "leftWrist"
            ],
            "width": 0.2932551319648094,
            "x": 53.0791788856305,
            "y": 47.78067885117493
          }
        },
        {
          "from_name": "kp-1",
          "id": "ASJYbyyIsZ",
          "image_rotation": 0,
          "original_height": 1080,
          "original_width": 1920,
          "parent_id": null,
          "source": "$img",
          "to_name": "img-1",
          "type": "keypointlabels",
          "value": {
            "keypointlabels": [
              "rightWrist"
            ],
            "width": 0.2932551319648094,
            "x": 48.82697947214076,
            "y": 31.33159268929504
          }
        },
        {
          "from_name": "kp-1",
          "id": "Rs40O8ED1x",
          "image_rotation": 0,
          "original_height": 1080,
          "original_width": 1920,
          "parent_id": null,
          "source": "$img",
          "to_name": "img-1",
          "type": "keypointlabels",
          "value": {
            "keypointlabels": [
              "leftHip"
            ],
            "width": 0.2932551319648094,
            "x": 52.05278592375367,
            "y": 48.825065274151434
          }
        },
        {
          "from_name": "kp-1",
          "id": "Lu1i-kx5bU",
          "image_rotation": 0,
          "original_height": 1080,
          "original_width": 1920,
          "parent_id": null,
          "source": "$img",
          "to_name": "img-1",
          "type": "keypointlabels",
          "value": {
            "keypointlabels": [
              "rightHip"
            ],
            "width": 0.2932551319648094,
            "x": 48.38709677419355,
            "y": 48.04177545691906
          }
        },
        {
          "from_name": "kp-1",
          "id": "u9Vf3neyje",
          "image_rotation": 0,
          "original_height": 1080,
          "original_width": 1920,
          "parent_id": null,
          "source": "$img",
          "to_name": "img-1",
          "type": "keypointlabels",
          "value": {
            "keypointlabels": [
              "leftKnee"
            ],
            "width": 0.2932551319648094,
            "x": 52.05278592375367,
            "y": 55.09138381201044
          }
        },
        {
          "from_name": "kp-1",
          "id": "yx7zbkjY9f",
          "image_rotation": 0,
          "original_height": 1080,
          "original_width": 1920,
          "parent_id": null,
          "source": "$img",
          "to_name": "img-1",
          "type": "keypointlabels",
          "value": {
            "keypointlabels": [
              "rightKnee"
            ],
            "width": 0.2932551319648094,
            "x": 48.97360703812317,
            "y": 55.09138381201044
          }
        },
        {
          "from_name": "kp-1",
          "id": "2W6NwqwyK_",
          "image_rotation": 0,
          "original_height": 1080,
          "original_width": 1920,
          "parent_id": null,
          "source": "$img",
          "to_name": "img-1",
          "type": "keypointlabels",
          "value": {
            "keypointlabels": [
              "leftAnkle"
            ],
            "width": 0.2932551319648094,
            "x": 52.34604105571847,
            "y": 62.40208877284595
          }
        },
        {
          "from_name": "kp-1",
          "id": "HdCnHTWa_G",
          "image_rotation": 0,
          "original_height": 1080,
          "original_width": 1920,
          "parent_id": null,
          "source": "$img",
          "to_name": "img-1",
          "type": "keypointlabels",
          "value": {
            "keypointlabels": [
              "rightAnkle"
            ],
            "width": 0.2932551319648094,
            "x": 48.82697947214076,
            "y": 62.66318537859008
          }
        }
      ]
    }
  ],
  "data": {
    "img": "/data/P004S00G10B50H40UC092000LC022000A000R0_08251032_091.jpg?d=%2Fhome%2Fyolo%2FSUTDDatasetProcess%2Fsplits4%2Fsplits4%2Flabel_00"
  },
  "id": 308,
  "task_path": "/home/yolo/SUTDDatasetProcess/splits4/splits4/label_00/P004S00G10B50H40UC092000LC022000A000R0_08251032_091.jpg"
}