{
  "completions": [
    {
      "created_at": 1602645952,
      "id": 441001,
      "lead_time": 12.687,
      "result": [
        {
          "from_name": "kp-1",
          "id": "mCIIEwABQ9",
          "image_rotation": 0,
          "original_height": 1080,
          "original_width": 1920,
          "parent_id": null,
          "source": "$img",
          "to_name": "img-1",
          "type": "keypointlabels",
          "value": {
            "keypointlabels": [
              "nose"
            ],
            "width": 0.26666666666666666,
            "x": 47.733333333333334,
            "y": 31.753554502369667
          }
        },
        {
          "from_name": "kp-1",
          "id": "iANlikpHkY",
          "image_rotation": 0,
          "original_height": 1080,
          "original_width": 1920,
          "parent_id": null,
          "source": "$img",
          "to_name": "img-1",
          "type": "keypointlabels",
          "value": {
            "keypointlabels": [
              "leftEye"
            ],
            "width": 0.26666666666666666,
            "x": 47.86666666666667,
            "y": 30.09478672985782
          }
        },
        {
          "from_name": "kp-1",
          "id": "OMTQDn52mm",
          "image_rotation": 0,
          "original_height": 1080,
          "original_width": 1920,
          "parent_id": null,
          "source": "$img",
          "to_name": "img-1",
          "type": "keypointlabels",
          "value": {
            "keypointlabels": [
              "rightEye"
            ],
            "width": 0.26666666666666666,
            "x": 46.666666666666664,
            "y": 29.85781990521327
          }
        },
        {
          "from_name": "kp-1",
          "id": "CfnYyL1thU",
          "image_rotation": 0,
          "original_height": 1080,
          "original_width": 1920,
          "parent_id": null,
          "source": "$img",
          "to_name": "img-1",
          "type": "keypointlabels",
          "value": {
            "keypointlabels": [
              "rightEar"
            ],
            "width": 0.26666666666666666,
            "x": 46.13333333333333,
            "y": 30.56872037914692
          }
        },
        {
          "from_name": "kp-1",
          "id": "l59fceAM95",
          "image_rotation": 0,
          "original_height": 1080,
          "original_width": 1920,
          "parent_id": null,
          "source": "$img",
          "to_name": "img-1",
          "type": "keypointlabels",
          "value": {
            "keypointlabels": [
              "leftShoulder"
            ],
            "width": 0.26666666666666666,
            "x": 49.46666666666667,
            "y": 33.88625592417062
          }
        },
        {
          "from_name": "kp-1",
          "id": "NE32kwsBNB",
          "image_rotation": 0,
          "original_height": 1080,
          "original_width": 1920,
          "parent_id": null,
          "source": "$img",
          "to_name": "img-1",
          "type": "keypointlabels",
          "value": {
            "keypointlabels": [
              "rightShoulder"
            ],
            "width": 0.26666666666666666,
            "x": 44.266666666666666,
            "y": 36.018957345971565
          }
        },
        {
          "from_name": "kp-1",
          "id": "ZpfA2dOsKX",
          "image_rotation": 0,
          "original_height": 1080,
          "original_width": 1920,
          "parent_id": null,
          "source": "$img",
          "to_name": "img-1",
          "type": "keypointlabels",
          "value": {
            "keypointlabels": [
              "leftElbow"
            ],
            "width": 0.26666666666666666,
            "x": 50.13333333333333,
            "y": 39.81042654028436
          }
        },
        {
          "from_name": "kp-1",
          "id": "NXNmPTvVQW",
          "image_rotation": 0,
          "original_height": 1080,
          "original_width": 1920,
          "parent_id": null,
          "source": "$img",
          "to_name": "img-1",
          "type": "keypointlabels",
          "value": {
            "keypointlabels": [
              "rightElbow"
            ],
            "width": 0.26666666666666666,
            "x": 43.733333333333334,
            "y": 42.654028436018955
          }
        },
        {
          "from_name": "kp-1",
          "id": "483H-pAn7c",
          "image_rotation": 0,
          "original_height": 1080,
          "original_width": 1920,
          "parent_id": null,
          "source": "$img",
          "to_name": "img-1",
          "type": "keypointlabels",
          "value": {
            "keypointlabels": [
              "leftWrist"
            ],
            "width": 0.26666666666666666,
            "x": 50.4,
            "y": 47.39336492890995
          }
        },
        {
          "from_name": "kp-1",
          "id": "myiHJT_gPw",
          "image_rotation": 0,
          "original_height": 1080,
          "original_width": 1920,
          "parent_id": null,
          "source": "$img",
          "to_name": "img-1",
          "type": "keypointlabels",
          "value": {
            "keypointlabels": [
              "rightWrist"
            ],
            "width": 0.26666666666666666,
            "x": 44.53333333333333,
            "y": 49.5260663507109
          }
        },
        {
          "from_name": "kp-1",
          "id": "BiRo3GUuQB",
          "image_rotation": 0,
          "original_height": 1080,
          "original_width": 1920,
          "parent_id": null,
          "source": "$img",
          "to_name": "img-1",
          "type": "keypointlabels",
          "value": {
            "keypointlabels": [
              "leftHip"
            ],
            "width": 0.26666666666666666,
            "x": 48.666666666666664,
            "y": 48.5781990521327
          }
        },
        {
          "from_name": "kp-1",
          "id": "NsrbaxXpUX",
          "image_rotation": 0,
          "original_height": 1080,
          "original_width": 1920,
          "parent_id": null,
          "source": "$img",
          "to_name": "img-1",
          "type": "keypointlabels",
          "value": {
            "keypointlabels": [
              "rightHip"
            ],
            "width": 0.26666666666666666,
            "x": 46.666666666666664,
            "y": 48.5781990521327
          }
        },
        {
          "from_name": "kp-1",
          "id": "WCOlcC2QEI",
          "image_rotation": 0,
          "original_height": 1080,
          "original_width": 1920,
          "parent_id": null,
          "source": "$img",
          "to_name": "img-1",
          "type": "keypointlabels",
          "value": {
            "keypointlabels": [
              "leftKnee"
            ],
            "width": 0.26666666666666666,
            "x": 48.93333333333333,
            "y": 55.92417061611374
          }
        },
        {
          "from_name": "kp-1",
          "id": "nyI_hzFw-4",
          "image_rotation": 0,
          "original_height": 1080,
          "original_width": 1920,
          "parent_id": null,
          "source": "$img",
          "to_name": "img-1",
          "type": "keypointlabels",
          "value": {
            "keypointlabels": [
              "rightKnee"
            ],
            "width": 0.26666666666666666,
            "x": 46,
            "y": 56.161137440758296
          }
        },
        {
          "from_name": "kp-1",
          "id": "TaeULsXHdl",
          "image_rotation": 0,
          "original_height": 1080,
          "original_width": 1920,
          "parent_id": null,
          "source": "$img",
          "to_name": "img-1",
          "type": "keypointlabels",
          "value": {
            "keypointlabels": [
              "leftAnkle"
            ],
            "width": 0.26666666666666666,
            "x": 49.06666666666667,
            "y": 60.90047393364929
          }
        },
        {
          "from_name": "kp-1",
          "id": "zZkqY-9Ebr",
          "image_rotation": 0,
          "original_height": 1080,
          "original_width": 1920,
          "parent_id": null,
          "source": "$img",
          "to_name": "img-1",
          "type": "keypointlabels",
          "value": {
            "keypointlabels": [
              "rightAnkle"
            ],
            "width": 0.26666666666666666,
            "x": 46.4,
            "y": 61.84834123222749
          }
        }
      ]
    }
  ],
  "data": {
    "img": "/data/P002S03G10B00H00UC062000LC092000A029R0_09071427_159.jpg?d=%2Fhome%2Fyolo%2FSUTDDatasetProcess%2Fsplits5%2Fsplits5%2Flabel_00"
  },
  "id": 441,
  "task_path": "/home/yolo/SUTDDatasetProcess/splits5/splits5/label_00/P002S03G10B00H00UC062000LC092000A029R0_09071427_159.jpg"
}