{
  "completions": [
    {
      "created_at": 1602599594,
      "id": 5001,
      "lead_time": 73.644,
      "result": [
        {
          "from_name": "kp-1",
          "id": "fzq0ag25Rb",
          "image_rotation": 0,
          "original_height": 1080,
          "original_width": 1920,
          "parent_id": null,
          "source": "$img",
          "to_name": "img-1",
          "type": "keypointlabels",
          "value": {
            "keypointlabels": [
              "nose"
            ],
            "width": 0.26666666666666666,
            "x": 47.6,
            "y": 34.834123222748815
          }
        },
        {
          "from_name": "kp-1",
          "id": "HTUQSrejlU",
          "image_rotation": 0,
          "original_height": 1080,
          "original_width": 1920,
          "parent_id": null,
          "source": "$img",
          "to_name": "img-1",
          "type": "keypointlabels",
          "value": {
            "keypointlabels": [
              "leftEye"
            ],
            "width": 0.26666666666666666,
            "x": 48.4,
            "y": 34.360189573459714
          }
        },
        {
          "from_name": "kp-1",
          "id": "ygh-a3SWB8",
          "image_rotation": 0,
          "original_height": 1080,
          "original_width": 1920,
          "parent_id": null,
          "source": "$img",
          "to_name": "img-1",
          "type": "keypointlabels",
          "value": {
            "keypointlabels": [
              "rightEye"
            ],
            "width": 0.26666666666666666,
            "x": 47.733333333333334,
            "y": 34.12322274881517
          }
        },
        {
          "from_name": "kp-1",
          "id": "0XBlDrtLQy",
          "image_rotation": 0,
          "original_height": 1080,
          "original_width": 1920,
          "parent_id": null,
          "source": "$img",
          "to_name": "img-1",
          "type": "keypointlabels",
          "value": {
            "keypointlabels": [
              "leftEar"
            ],
            "width": 0.26666666666666666,
            "x": 50,
            "y": 35.54502369668246
          }
        },
        {
          "from_name": "kp-1",
          "id": "bnMfOzKpBL",
          "image_rotation": 0,
          "original_height": 1080,
          "original_width": 1920,
          "parent_id": null,
          "source": "$img",
          "to_name": "img-1",
          "type": "keypointlabels",
          "value": {
            "keypointlabels": [
              "leftShoulder"
            ],
            "width": 0.26666666666666666,
            "x": 51.6,
            "y": 42.18009478672986
          }
        },
        {
          "from_name": "kp-1",
          "id": "5I6sTI1-6B",
          "image_rotation": 0,
          "original_height": 1080,
          "original_width": 1920,
          "parent_id": null,
          "source": "$img",
          "to_name": "img-1",
          "type": "keypointlabels",
          "value": {
            "keypointlabels": [
              "rightShoulder"
            ],
            "width": 0.26666666666666666,
            "x": 47.6,
            "y": 41.23222748815166
          }
        },
        {
          "from_name": "kp-1",
          "id": "ET0RLGPT8l",
          "image_rotation": 0,
          "original_height": 1080,
          "original_width": 1920,
          "parent_id": null,
          "source": "$img",
          "to_name": "img-1",
          "type": "keypointlabels",
          "value": {
            "keypointlabels": [
              "leftElbow"
            ],
            "width": 0.26666666666666666,
            "x": 50.8,
            "y": 50.947867298578196
          }
        },
        {
          "from_name": "kp-1",
          "id": "QaOKF7FXqN",
          "image_rotation": 0,
          "original_height": 1080,
          "original_width": 1920,
          "parent_id": null,
          "source": "$img",
          "to_name": "img-1",
          "type": "keypointlabels",
          "value": {
            "keypointlabels": [
              "rightElbow"
            ],
            "width": 0.26666666666666666,
            "x": 46.93333333333333,
            "y": 49.052132701421804
          }
        },
        {
          "from_name": "kp-1",
          "id": "V5S0OCyQy1",
          "image_rotation": 0,
          "original_height": 1080,
          "original_width": 1920,
          "parent_id": null,
          "source": "$img",
          "to_name": "img-1",
          "type": "keypointlabels",
          "value": {
            "keypointlabels": [
              "leftWrist"
            ],
            "width": 0.26666666666666666,
            "x": 50.13333333333333,
            "y": 58.056872037914694
          }
        },
        {
          "from_name": "kp-1",
          "id": "i_2Vx870qy",
          "image_rotation": 0,
          "original_height": 1080,
          "original_width": 1920,
          "parent_id": null,
          "source": "$img",
          "to_name": "img-1",
          "type": "keypointlabels",
          "value": {
            "keypointlabels": [
              "rightWrist"
            ],
            "width": 0.26666666666666666,
            "x": 46.8,
            "y": 54.73933649289099
          }
        },
        {
          "from_name": "kp-1",
          "id": "_sDZHdKw1J",
          "image_rotation": 0,
          "original_height": 1080,
          "original_width": 1920,
          "parent_id": null,
          "source": "$img",
          "to_name": "img-1",
          "type": "keypointlabels",
          "value": {
            "keypointlabels": [
              "leftHip"
            ],
            "width": 0.26666666666666666,
            "x": 49.06666666666667,
            "y": 57.81990521327014
          }
        },
        {
          "from_name": "kp-1",
          "id": "FtVRIlkltp",
          "image_rotation": 0,
          "original_height": 1080,
          "original_width": 1920,
          "parent_id": null,
          "source": "$img",
          "to_name": "img-1",
          "type": "keypointlabels",
          "value": {
            "keypointlabels": [
              "rightHip"
            ],
            "width": 0.26666666666666666,
            "x": 47.6,
            "y": 55.92417061611374
          }
        },
        {
          "from_name": "kp-1",
          "id": "nDL6wd-ZeW",
          "image_rotation": 0,
          "original_height": 1080,
          "original_width": 1920,
          "parent_id": null,
          "source": "$img",
          "to_name": "img-1",
          "type": "keypointlabels",
          "value": {
            "keypointlabels": [
              "leftKnee"
            ],
            "width": 0.26666666666666666,
            "x": 49.6,
            "y": 67.06161137440758
          }
        },
        {
          "from_name": "kp-1",
          "id": "tOHTn8Vpyi",
          "image_rotation": 0,
          "original_height": 1080,
          "original_width": 1920,
          "parent_id": null,
          "source": "$img",
          "to_name": "img-1",
          "type": "keypointlabels",
          "value": {
            "keypointlabels": [
              "rightKnee"
            ],
            "width": 0.26666666666666666,
            "x": 47.46666666666667,
            "y": 65.87677725118483
          }
        },
        {
          "from_name": "kp-1",
          "id": "vLbf_FUpLL",
          "image_rotation": 0,
          "original_height": 1080,
          "original_width": 1920,
          "parent_id": null,
          "source": "$img",
          "to_name": "img-1",
          "type": "keypointlabels",
          "value": {
            "keypointlabels": [
              "leftAnkle"
            ],
            "width": 0.26666666666666666,
            "x": 50.266666666666666,
            "y": 74.88151658767772
          }
        },
        {
          "from_name": "kp-1",
          "id": "XdzZOFhZRS",
          "image_rotation": 0,
          "original_height": 1080,
          "original_width": 1920,
          "parent_id": null,
          "source": "$img",
          "to_name": "img-1",
          "type": "keypointlabels",
          "value": {
            "keypointlabels": [
              "rightAnkle"
            ],
            "width": 0.26666666666666666,
            "x": 49.333333333333336,
            "y": 74.17061611374407
          }
        }
      ]
    }
  ],
  "data": {
    "img": "/data/P079S01G10B00H10UC022000LC021000A029R0_09171513_137.jpg?d=%2Fhome%2Fyolo%2FSUTDDatasetProcess%2Fsplits5%2Fsplits5%2Flabel_08"
  },
  "id": 5,
  "task_path": "/home/yolo/SUTDDatasetProcess/splits5/splits5/label_08/P079S01G10B00H10UC022000LC021000A029R0_09171513_137.jpg"
}