{
  "completions": [
    {
      "created_at": 1602157417,
      "id": 215001,
      "lead_time": 141.454,
      "result": [
        {
          "from_name": "kp-1",
          "id": "6M2YXbbzl-",
          "image_rotation": 0,
          "original_height": 1080,
          "original_width": 1920,
          "parent_id": null,
          "source": "$img",
          "to_name": "img-1",
          "type": "keypointlabels",
          "value": {
            "keypointlabels": [
              "nose"
            ],
            "width": 0.26666666666666666,
            "x": 58.53333333333333,
            "y": 17.298578199052134
          }
        },
        {
          "from_name": "kp-1",
          "id": "_mGGf4SFQV",
          "image_rotation": 0,
          "original_height": 1080,
          "original_width": 1920,
          "parent_id": null,
          "source": "$img",
          "to_name": "img-1",
          "type": "keypointlabels",
          "value": {
            "keypointlabels": [
              "leftEye"
            ],
            "width": 0.26666666666666666,
            "x": 58.93333333333333,
            "y": 16.350710900473935
          }
        },
        {
          "from_name": "kp-1",
          "id": "x37Rwyds1V",
          "image_rotation": 0,
          "original_height": 1080,
          "original_width": 1920,
          "parent_id": null,
          "source": "$img",
          "to_name": "img-1",
          "type": "keypointlabels",
          "value": {
            "keypointlabels": [
              "rightEye"
            ],
            "width": 0.26666666666666666,
            "x": 58.4,
            "y": 16.113744075829384
          }
        },
        {
          "from_name": "kp-1",
          "id": "aFrPDQEt2a",
          "image_rotation": 0,
          "original_height": 1080,
          "original_width": 1920,
          "parent_id": null,
          "source": "$img",
          "to_name": "img-1",
          "type": "keypointlabels",
          "value": {
            "keypointlabels": [
              "leftEar"
            ],
            "width": 0.26666666666666666,
            "x": 59.46666666666667,
            "y": 16.587677725118482
          }
        },
        {
          "from_name": "kp-1",
          "id": "RVsmQv5ciA",
          "image_rotation": 0,
          "original_height": 1080,
          "original_width": 1920,
          "parent_id": null,
          "source": "$img",
          "to_name": "img-1",
          "type": "keypointlabels",
          "value": {
            "keypointlabels": [
              "rightEar"
            ],
            "width": 0.26666666666666666,
            "x": 57.86666666666667,
            "y": 16.350710900473935
          }
        },
        {
          "from_name": "kp-1",
          "id": "1v-LxQcS22",
          "image_rotation": 0,
          "original_height": 1080,
          "original_width": 1920,
          "parent_id": null,
          "source": "$img",
          "to_name": "img-1",
          "type": "keypointlabels",
          "value": {
            "keypointlabels": [
              "rightShoulder"
            ],
            "width": 0.26666666666666666,
            "x": 57.2,
            "y": 17.77251184834123
          }
        },
        {
          "from_name": "kp-1",
          "id": "9uv_8EcvoB",
          "image_rotation": 0,
          "original_height": 1080,
          "original_width": 1920,
          "parent_id": null,
          "source": "$img",
          "to_name": "img-1",
          "type": "keypointlabels",
          "value": {
            "keypointlabels": [
              "rightElbow"
            ],
            "width": 0.26666666666666666,
            "x": 56.666666666666664,
            "y": 22.03791469194313
          }
        },
        {
          "from_name": "kp-1",
          "id": "bVyd0v-1VO",
          "image_rotation": 0,
          "original_height": 1080,
          "original_width": 1920,
          "parent_id": null,
          "source": "$img",
          "to_name": "img-1",
          "type": "keypointlabels",
          "value": {
            "keypointlabels": [
              "rightWrist"
            ],
            "width": 0.26666666666666666,
            "x": 56.4,
            "y": 24.407582938388625
          }
        },
        {
          "from_name": "kp-1",
          "id": "oPydvzn75M",
          "image_rotation": 0,
          "original_height": 1080,
          "original_width": 1920,
          "parent_id": null,
          "source": "$img",
          "to_name": "img-1",
          "type": "keypointlabels",
          "value": {
            "keypointlabels": [
              "rightHip"
            ],
            "width": 0.26666666666666666,
            "x": 56.666666666666664,
            "y": 26.066350710900473
          }
        },
        {
          "from_name": "kp-1",
          "id": "ke1Dye1Wju",
          "image_rotation": 0,
          "original_height": 1080,
          "original_width": 1920,
          "parent_id": null,
          "source": "$img",
          "to_name": "img-1",
          "type": "keypointlabels",
          "value": {
            "keypointlabels": [
              "rightKnee"
            ],
            "width": 0.26666666666666666,
            "x": 57.46666666666667,
            "y": 29.38388625592417
          }
        },
        {
          "from_name": "kp-1",
          "id": "R6Yt9tpboy",
          "image_rotation": 0,
          "original_height": 1080,
          "original_width": 1920,
          "parent_id": null,
          "source": "$img",
          "to_name": "img-1",
          "type": "keypointlabels",
          "value": {
            "keypointlabels": [
              "rightAnkle"
            ],
            "width": 0.26666666666666666,
            "x": 57.333333333333336,
            "y": 31.753554502369667
          }
        }
      ]
    }
  ],
  "data": {
    "img": "/data/P095S00G10B00H00UC072000LC021000A005R0_09212012_128.jpg?d=%2Fhome%2Flitianjiao%2FSUTDDatasetProcess%2Fsplits%2Flabel_01"
  },
  "id": 215,
  "task_path": "/home/litianjiao/SUTDDatasetProcess/splits/label_01/P095S00G10B00H00UC072000LC021000A005R0_09212012_128.jpg"
}