{
  "completions": [
    {
      "created_at": 1601296298,
      "id": 345001,
      "lead_time": 17.065,
      "result": [
        {
          "from_name": "kp-1",
          "id": "0ew8GdRWQv",
          "image_rotation": 0,
          "original_height": 1080,
          "original_width": 1920,
          "parent_id": null,
          "source": "$img",
          "to_name": "img-1",
          "type": "keypointlabels",
          "value": {
            "keypointlabels": [
              "nose"
            ],
            "width": 0.26666666666666666,
            "x": 50.4,
            "y": 34.834123222748815
          }
        },
        {
          "from_name": "kp-1",
          "id": "nTaKcy8ziy",
          "image_rotation": 0,
          "original_height": 1080,
          "original_width": 1920,
          "parent_id": null,
          "source": "$img",
          "to_name": "img-1",
          "type": "keypointlabels",
          "value": {
            "keypointlabels": [
              "leftEye"
            ],
            "width": 0.26666666666666666,
            "x": 50.8,
            "y": 34.360189573459714
          }
        },
        {
          "from_name": "kp-1",
          "id": "ltoKJPki6v",
          "image_rotation": 0,
          "original_height": 1080,
          "original_width": 1920,
          "parent_id": null,
          "source": "$img",
          "to_name": "img-1",
          "type": "keypointlabels",
          "value": {
            "keypointlabels": [
              "rightEye"
            ],
            "width": 0.26666666666666666,
            "x": 49.86666666666667,
            "y": 34.360189573459714
          }
        },
        {
          "from_name": "kp-1",
          "id": "EA6p9OSuAg",
          "image_rotation": 0,
          "original_height": 1080,
          "original_width": 1920,
          "parent_id": null,
          "source": "$img",
          "to_name": "img-1",
          "type": "keypointlabels",
          "value": {
            "keypointlabels": [
              "leftEar"
            ],
            "width": 0.26666666666666666,
            "x": 51.733333333333334,
            "y": 33.649289099526065
          }
        },
        {
          "from_name": "kp-1",
          "id": "LHRP8f41hK",
          "image_rotation": 0,
          "original_height": 1080,
          "original_width": 1920,
          "parent_id": null,
          "source": "$img",
          "to_name": "img-1",
          "type": "keypointlabels",
          "value": {
            "keypointlabels": [
              "rightEar"
            ],
            "width": 0.26666666666666666,
            "x": 49.333333333333336,
            "y": 33.88625592417062
          }
        },
        {
          "from_name": "kp-1",
          "id": "DyrqJkrKJo",
          "image_rotation": 0,
          "original_height": 1080,
          "original_width": 1920,
          "parent_id": null,
          "source": "$img",
          "to_name": "img-1",
          "type": "keypointlabels",
          "value": {
            "keypointlabels": [
              "leftShoulder"
            ],
            "width": 0.26666666666666666,
            "x": 53.6,
            "y": 38.86255924170616
          }
        },
        {
          "from_name": "kp-1",
          "id": "zn4hwsgGoB",
          "image_rotation": 0,
          "original_height": 1080,
          "original_width": 1920,
          "parent_id": null,
          "source": "$img",
          "to_name": "img-1",
          "type": "keypointlabels",
          "value": {
            "keypointlabels": [
              "rightShoulder"
            ],
            "width": 0.26666666666666666,
            "x": 48.4,
            "y": 38.388625592417064
          }
        },
        {
          "from_name": "kp-1",
          "id": "ZACCoIMbqd",
          "image_rotation": 0,
          "original_height": 1080,
          "original_width": 1920,
          "parent_id": null,
          "source": "$img",
          "to_name": "img-1",
          "type": "keypointlabels",
          "value": {
            "keypointlabels": [
              "leftElbow"
            ],
            "width": 0.26666666666666666,
            "x": 54.4,
            "y": 43.838862559241704
          }
        },
        {
          "from_name": "kp-1",
          "id": "_b619tFS6P",
          "image_rotation": 0,
          "original_height": 1080,
          "original_width": 1920,
          "parent_id": null,
          "source": "$img",
          "to_name": "img-1",
          "type": "keypointlabels",
          "value": {
            "keypointlabels": [
              "rightElbow"
            ],
            "width": 0.26666666666666666,
            "x": 47.2,
            "y": 44.312796208530806
          }
        },
        {
          "from_name": "kp-1",
          "id": "axEym4ImwN",
          "image_rotation": 0,
          "original_height": 1080,
          "original_width": 1920,
          "parent_id": null,
          "source": "$img",
          "to_name": "img-1",
          "type": "keypointlabels",
          "value": {
            "keypointlabels": [
              "leftWrist"
            ],
            "width": 0.26666666666666666,
            "x": 52.4,
            "y": 46.682464454976305
          }
        },
        {
          "from_name": "kp-1",
          "id": "sL_xjqGLal",
          "image_rotation": 0,
          "original_height": 1080,
          "original_width": 1920,
          "parent_id": null,
          "source": "$img",
          "to_name": "img-1",
          "type": "keypointlabels",
          "value": {
            "keypointlabels": [
              "rightWrist"
            ],
            "width": 0.26666666666666666,
            "x": 48.4,
            "y": 42.18009478672986
          }
        },
        {
          "from_name": "kp-1",
          "id": "NKABtqwufb",
          "image_rotation": 0,
          "original_height": 1080,
          "original_width": 1920,
          "parent_id": null,
          "source": "$img",
          "to_name": "img-1",
          "type": "keypointlabels",
          "value": {
            "keypointlabels": [
              "leftHip"
            ],
            "width": 0.26666666666666666,
            "x": 53.2,
            "y": 49.052132701421804
          }
        },
        {
          "from_name": "kp-1",
          "id": "4Q1caPFqr9",
          "image_rotation": 0,
          "original_height": 1080,
          "original_width": 1920,
          "parent_id": null,
          "source": "$img",
          "to_name": "img-1",
          "type": "keypointlabels",
          "value": {
            "keypointlabels": [
              "rightHip"
            ],
            "width": 0.26666666666666666,
            "x": 49.86666666666667,
            "y": 49.052132701421804
          }
        },
        {
          "from_name": "kp-1",
          "id": "YgkumrDcID",
          "image_rotation": 0,
          "original_height": 1080,
          "original_width": 1920,
          "parent_id": null,
          "source": "$img",
          "to_name": "img-1",
          "type": "keypointlabels",
          "value": {
            "keypointlabels": [
              "leftKnee"
            ],
            "width": 0.26666666666666666,
            "x": 53.6,
            "y": 59.47867298578199
          }
        },
        {
          "from_name": "kp-1",
          "id": "ae-VueyQQX",
          "image_rotation": 0,
          "original_height": 1080,
          "original_width": 1920,
          "parent_id": null,
          "source": "$img",
          "to_name": "img-1",
          "type": "keypointlabels",
          "value": {
            "keypointlabels": [
              "rightKnee"
            ],
            "width": 0.26666666666666666,
            "x": 49.86666666666667,
            "y": 59.47867298578199
          }
        },
        {
          "from_name": "kp-1",
          "id": "hgqWrB4WwV",
          "image_rotation": 0,
          "original_height": 1080,
          "original_width": 1920,
          "parent_id": null,
          "source": "$img",
          "to_name": "img-1",
          "type": "keypointlabels",
          "value": {
            "keypointlabels": [
              "leftAnkle"
            ],
            "width": 0.26666666666666666,
            "x": 54.266666666666666,
            "y": 69.90521327014218
          }
        },
        {
          "from_name": "kp-1",
          "id": "ddiTa1HR2B",
          "image_rotation": 0,
          "original_height": 1080,
          "original_width": 1920,
          "parent_id": null,
          "source": "$img",
          "to_name": "img-1",
          "type": "keypointlabels",
          "value": {
            "keypointlabels": [
              "rightAnkle"
            ],
            "width": 0.26666666666666666,
            "x": 51.733333333333334,
            "y": 69.19431279620854
          }
        }
      ]
    }
  ],
  "data": {
    "img": "/data/P073S00G10B00H00UC022000LC021000A001R0_09151645_190.jpg?d=%2Fdata%2Furop_action%2FSUTDActionDataset%2Flabel_cropped_data_storage%2Fraw_data_3"
  },
  "id": 345,
  "task_path": "/data/urop_action/SUTDActionDataset/label_cropped_data_storage/raw_data_3/P073S00G10B00H00UC022000LC021000A001R0_09151645_190.jpg"
}