{
  "completions": [
    {
      "created_at": 1602490876,
      "id": 847001,
      "lead_time": 29.097,
      "result": [
        {
          "from_name": "kp-1",
          "id": "EbLylYrbn6",
          "image_rotation": 0,
          "original_height": 1080,
          "original_width": 1920,
          "parent_id": null,
          "source": "$img",
          "to_name": "img-1",
          "type": "keypointlabels",
          "value": {
            "keypointlabels": [
              "nose"
            ],
            "width": 0.26666666666666666,
            "x": 46,
            "y": 32.93838862559242
          }
        },
        {
          "from_name": "kp-1",
          "id": "CUOC8Q90IR",
          "image_rotation": 0,
          "original_height": 1080,
          "original_width": 1920,
          "parent_id": null,
          "source": "$img",
          "to_name": "img-1",
          "type": "keypointlabels",
          "value": {
            "keypointlabels": [
              "leftEye"
            ],
            "width": 0.26666666666666666,
            "x": 46.666666666666664,
            "y": 31.990521327014218
          }
        },
        {
          "from_name": "kp-1",
          "id": "QRpmHo--QM",
          "image_rotation": 0,
          "original_height": 1080,
          "original_width": 1920,
          "parent_id": null,
          "source": "$img",
          "to_name": "img-1",
          "type": "keypointlabels",
          "value": {
            "keypointlabels": [
              "rightEye"
            ],
            "width": 0.26666666666666666,
            "x": 45.733333333333334,
            "y": 31.990521327014218
          }
        },
        {
          "from_name": "kp-1",
          "id": "Y4jNT10QXc",
          "image_rotation": 0,
          "original_height": 1080,
          "original_width": 1920,
          "parent_id": null,
          "source": "$img",
          "to_name": "img-1",
          "type": "keypointlabels",
          "value": {
            "keypointlabels": [
              "leftEar"
            ],
            "width": 0.26666666666666666,
            "x": 47.86666666666667,
            "y": 32.93838862559242
          }
        },
        {
          "from_name": "kp-1",
          "id": "cuIDkkv6Iv",
          "image_rotation": 0,
          "original_height": 1080,
          "original_width": 1920,
          "parent_id": null,
          "source": "$img",
          "to_name": "img-1",
          "type": "keypointlabels",
          "value": {
            "keypointlabels": [
              "rightEar"
            ],
            "width": 0.26666666666666666,
            "x": 45.333333333333336,
            "y": 32.93838862559242
          }
        },
        {
          "from_name": "kp-1",
          "id": "9hywgt_Sp4",
          "image_rotation": 0,
          "original_height": 1080,
          "original_width": 1920,
          "parent_id": null,
          "source": "$img",
          "to_name": "img-1",
          "type": "keypointlabels",
          "value": {
            "keypointlabels": [
              "leftShoulder"
            ],
            "width": 0.26666666666666666,
            "x": 49.333333333333336,
            "y": 36.96682464454976
          }
        },
        {
          "from_name": "kp-1",
          "id": "UPm5dNNiZ6",
          "image_rotation": 0,
          "original_height": 1080,
          "original_width": 1920,
          "parent_id": null,
          "source": "$img",
          "to_name": "img-1",
          "type": "keypointlabels",
          "value": {
            "keypointlabels": [
              "rightShoulder"
            ],
            "width": 0.26666666666666666,
            "x": 44.93333333333333,
            "y": 35.54502369668246
          }
        },
        {
          "from_name": "kp-1",
          "id": "2iN-uZvkUJ",
          "image_rotation": 0,
          "original_height": 1080,
          "original_width": 1920,
          "parent_id": null,
          "source": "$img",
          "to_name": "img-1",
          "type": "keypointlabels",
          "value": {
            "keypointlabels": [
              "leftElbow"
            ],
            "width": 0.26666666666666666,
            "x": 49.06666666666667,
            "y": 42.89099526066351
          }
        },
        {
          "from_name": "kp-1",
          "id": "OxOIQZ-MM6",
          "image_rotation": 0,
          "original_height": 1080,
          "original_width": 1920,
          "parent_id": null,
          "source": "$img",
          "to_name": "img-1",
          "type": "keypointlabels",
          "value": {
            "keypointlabels": [
              "rightElbow"
            ],
            "width": 0.26666666666666666,
            "x": 43.6,
            "y": 40.758293838862556
          }
        },
        {
          "from_name": "kp-1",
          "id": "0sxUWG2g47",
          "image_rotation": 0,
          "original_height": 1080,
          "original_width": 1920,
          "parent_id": null,
          "source": "$img",
          "to_name": "img-1",
          "type": "keypointlabels",
          "value": {
            "keypointlabels": [
              "leftWrist"
            ],
            "width": 0.26666666666666666,
            "x": 42.13333333333333,
            "y": 40.99526066350711
          }
        },
        {
          "from_name": "kp-1",
          "id": "LHoe8IQlkw",
          "image_rotation": 0,
          "original_height": 1080,
          "original_width": 1920,
          "parent_id": null,
          "source": "$img",
          "to_name": "img-1",
          "type": "keypointlabels",
          "value": {
            "keypointlabels": [
              "rightWrist"
            ],
            "width": 0.26666666666666666,
            "x": 46.53333333333333,
            "y": 41.23222748815166
          }
        },
        {
          "from_name": "kp-1",
          "id": "8QauLPG7gu",
          "image_rotation": 0,
          "original_height": 1080,
          "original_width": 1920,
          "parent_id": null,
          "source": "$img",
          "to_name": "img-1",
          "type": "keypointlabels",
          "value": {
            "keypointlabels": [
              "leftHip"
            ],
            "width": 0.26666666666666666,
            "x": 48,
            "y": 49.052132701421804
          }
        },
        {
          "from_name": "kp-1",
          "id": "t9Ax8XEJLX",
          "image_rotation": 0,
          "original_height": 1080,
          "original_width": 1920,
          "parent_id": null,
          "source": "$img",
          "to_name": "img-1",
          "type": "keypointlabels",
          "value": {
            "keypointlabels": [
              "rightHip"
            ],
            "width": 0.26666666666666666,
            "x": 45.333333333333336,
            "y": 48.81516587677725
          }
        },
        {
          "from_name": "kp-1",
          "id": "icjTLQvW0J",
          "image_rotation": 0,
          "original_height": 1080,
          "original_width": 1920,
          "parent_id": null,
          "source": "$img",
          "to_name": "img-1",
          "type": "keypointlabels",
          "value": {
            "keypointlabels": [
              "leftKnee"
            ],
            "width": 0.26666666666666666,
            "x": 47.46666666666667,
            "y": 57.10900473933649
          }
        },
        {
          "from_name": "kp-1",
          "id": "as4v6xBOYv",
          "image_rotation": 0,
          "original_height": 1080,
          "original_width": 1920,
          "parent_id": null,
          "source": "$img",
          "to_name": "img-1",
          "type": "keypointlabels",
          "value": {
            "keypointlabels": [
              "rightKnee"
            ],
            "width": 0.26666666666666666,
            "x": 45.2,
            "y": 56.872037914691944
          }
        },
        {
          "from_name": "kp-1",
          "id": "fr98f8gt4N",
          "image_rotation": 0,
          "original_height": 1080,
          "original_width": 1920,
          "parent_id": null,
          "source": "$img",
          "to_name": "img-1",
          "type": "keypointlabels",
          "value": {
            "keypointlabels": [
              "leftAnkle"
            ],
            "width": 0.26666666666666666,
            "x": 46.8,
            "y": 63.03317535545024
          }
        },
        {
          "from_name": "kp-1",
          "id": "5td61gzkbQ",
          "image_rotation": 0,
          "original_height": 1080,
          "original_width": 1920,
          "parent_id": null,
          "source": "$img",
          "to_name": "img-1",
          "type": "keypointlabels",
          "value": {
            "keypointlabels": [
              "rightAnkle"
            ],
            "width": 0.26666666666666666,
            "x": 45.333333333333336,
            "y": 62.322274881516584
          }
        }
      ]
    }
  ],
  "data": {
    "img": "/data/P115S18G10B00H00UC041000LC021000A009R0_10021556_242.jpg?d=%2Fhome%2Flitianjiao%2FSUTDDatasetProcess%2Fsplits2%2Flabel_02"
  },
  "id": 847,
  "task_path": "/home/litianjiao/SUTDDatasetProcess/splits2/label_02/P115S18G10B00H00UC041000LC021000A009R0_10021556_242.jpg"
}